README.rst
setup.cfg
setup.py
igd/__init__.py
igd/__main__.py
igd/core.py
igd/proto.py
igd/soap.py
igd/ssdp.py
igd.egg-info/PKG-INFO
igd.egg-info/SOURCES.txt
igd.egg-info/dependency_links.txt
igd.egg-info/entry_points.txt
igd.egg-info/requires.txt
igd.egg-info/top_level.txt