Metadata-Version: 1.1
Name: igd
Version: 0.1.1
Summary: IGD management CLI tool.
Home-page: https://github.com/povilasb/pyigd
Author: Povilas Balciunas
Author-email: balciunas90@gmail.com
License: MIT
Platform: UNKNOWN
Classifier: Programming Language :: Python :: 3.6
Classifier: Operating System :: POSIX :: Linux
Classifier: Natural Language :: English
Classifier: Development Status :: 3 - Alpha
Classifier: Topic :: Utilities
Classifier: Topic :: System :: Networking
